siegert_scatter/__init__.py
siegert_scatter/__main__.py
siegert_scatter/bessel_zeros.py
siegert_scatter/cli.py
siegert_scatter/cross_section.py
siegert_scatter/perturbation.py
siegert_scatter/polynomials.py
siegert_scatter/quadrature.py
siegert_scatter/tise.py
siegert_scatter/units.py
siegert_scatter-1.0.0.dist-info/WHEEL
siegert_scatter-1.0.0.dist-info/entry_points.txt
siegert_scatter-1.0.0.dist-info/METADATA
siegert_scatter-1.0.0.dist-info/RECORD
