Metadata-Version: 2.3
Name: siegert-scatter
Version: 1.0.0
Summary: Compute radial (partial-wave) Schrödinger scattering using the Siegert pseudostate (SPS) method, producing S-matrices, cross sections, Wigner time delays, and scattering lengths for user-defined potentials.
Keywords: scattering,quantum mechanics,Siegert pseudostates,S-matrix,cross section,Wigner time delay,scattering length,partial-wave expansion
Author: Anatoli Tsinovoy
Author-email: Anatoli Tsinovoy <anatoli.tsinovoy@gmail.com>
License: MIT License
Classifier: License :: OSI Approved :: MIT License
Classifier: Programming Language :: Python :: 3.13
Classifier: Topic :: Scientific/Engineering :: Physics
Classifier: Intended Audience :: Science/Research
Classifier: Operating System :: OS Independent
Requires-Dist: numpy>=2.4.0
Requires-Dist: scipy>=1.16.3
Requires-Python: >=3.13
Project-URL: Repository, https://github.com/anatoli-tsinovoy/siegert-scatter
Project-URL: Issues, https://github.com/anatoli-tsinovoy/siegert-scatter/issues
Project-URL: Changelog, https://github.com/anatoli-tsinovoy/siegert-scatter/releases
Project-URL: DOI, https://doi.org/10.5281/zenodo.18190655
Project-URL: Zenodo, https://doi.org/10.5281/zenodo.18190655
